{
    "key": "group_5de51e82423c9",
    "title": "User Fields",
    "fields": [
        {
            "key": "field_5de5210a4386f",
            "label": "User Rooms",
            "name": "user_rooms",
            "type": "relationship",
            "instructions": "Please select the rooms visible for the current user",
            "required": 0,
            "conditional_logic": 0,
            "wrapper": {
                "width": "",
                "class": "",
                "id": ""
            },
            "post_type": [
                "room"
            ],
            "taxonomy": "",
            "filters": [
                "search",
                "post_type",
                "taxonomy"
            ],
            "elements": [
                "featured_image"
            ],
            "min": "",
            "max": "",
            "return_format": "object"
        },
        {
            "key": "field_5de547991ebcb",
            "label": "Personalised Introduction",
            "name": "personalised_intro",
            "type": "textarea",
            "instructions": "",
            "required": 0,
            "conditional_logic": 0,
            "wrapper": {
                "width": "",
                "class": "",
                "id": ""
            },
            "default_value": "",
            "placeholder": "",
            "maxlength": "",
            "rows": "",
            "new_lines": ""
        },
        {
            "key": "field_5de64b00a2d94",
            "label": "Featured Image",
            "name": "featured_image",
            "type": "image",
            "instructions": "",
            "required": 0,
            "conditional_logic": 0,
            "wrapper": {
                "width": "",
                "class": "",
                "id": ""
            },
            "return_format": "url",
            "preview_size": "large",
            "library": "all",
            "min_width": "",
            "min_height": "",
            "min_size": "",
            "max_width": "",
            "max_height": "",
            "max_size": "",
            "mime_types": ""
        }
    ],
    "location": [
        [
            {
                "param": "user_form",
                "operator": "==",
                "value": "all"
            }
        ]
    ],
    "menu_order": 0,
    "position": "normal",
    "style": "default",
    "label_placement": "left",
    "instruction_placement": "label",
    "hide_on_screen": "",
    "active": 1,
    "description": "",
    "modified": 1575373590
}